pytorch_axe/__init__.py
pytorch_axe/layers.py
pytorch_axe/monitor.py
pytorch_axe/training.py
pytorch_axe-0.1.20.dist-info/WHEEL
pytorch_axe-0.1.20.dist-info/METADATA
pytorch_axe-0.1.20.dist-info/RECORD
